{
  "project_info": {
    "project_number": "1004950734460",
    "firebase_url": "https://jokenpokemon-cdaa7.firebaseio.com",
    "project_id": "jokenpokemon-cdaa7",
    "storage_bucket": "jokenpokemon-cdaa7.appspot.com"
  },
  "client": [
    {
      "client_info": {
        "mobilesdk_app_id": "1:1004950734460:android:914d6666ebf5647c",
        "android_client_info": {
          "package_name": "com.jokenpokemon.pedrolopes.jokenpokemon"
        }
      },
      "oauth_client": [
        {
          "client_id": "1004950734460-gra710rg0nbq5ugirt4gcuvjmnbm5ne2.apps.googleusercontent.com",
          "client_type": 1,
          "android_info": {
            "package_name": "com.jokenpokemon.pedrolopes.jokenpokemon",
            "certificate_hash": "beb224284730e1ec2ea6857c4e52af0c0438cd6c"
          }
        },
        {
          "client_id": "1004950734460-nii5h0gtvqefhm6bisnvfqtukhkupos9.apps.googleusercontent.com",
          "client_type": 3
        }
      ],
      "api_key": [
        {
          "current_key": "AIzaSyAVMBdZo8pnDF5axrCKv_MERy3N9djvJsQ"
        }
      ],
      "services": {
        "analytics_service": {
          "status": 1
        },
        "appinvite_service": {
          "status": 2,
          "other_platform_oauth_client": [
            {
              "client_id": "1004950734460-nii5h0gtvqefhm6bisnvfqtukhkupos9.apps.googleusercontent.com",
              "client_type": 3
            }
          ]
        },
        "ads_service": {
          "status": 2
        }
      }
    }
  ],
  "configuration_version": "1"
}